[{"id":"0OVaEbtWPhsZU9ReQnLE","createdAt":{"_seconds":1590827732,"_nanoseconds":276000000},"category_ids":["mskRjk1CHCvdWsURmmvz"],"title":"Travel","updatedAt":{"_seconds":1590827732,"_nanoseconds":276000000},"type_ids":["CF0uN3y5sZr9ZLnunaEy"]},{"id":"0VpHpUQuUkwBhEKtX4uJ","type_id":"Dzmxt8ehIp2ZLhBrXghY","createdAt":{"_seconds":1587546475,"_nanoseconds":23000000},"category_ids":["g2llU0ofWnYUFdvSh7Tn"],"title":"Nechlaces","updatedAt":{"_seconds":1587546475,"_nanoseconds":23000000},"type_ids":["Dzmxt8ehIp2ZLhBrXghY"]},{"title":"Heels","updatedAt":{"_seconds":1582538437,"_nanoseconds":562000000},"type_ids":["L3nCd0aPr9pOAbKNaAcW"],"id":"0Xd0DRwxLybinKMvZWqX","type_id":"L3nCd0aPr9pOAbKNaAcW","createdAt":{"_seconds":1582538437,"_nanoseconds":562000000},"category_ids":["g2llU0ofWnYUFdvSh7Tn"]},{"id":"0XjyOTFfMc4u05Q7gq4M","title":"Loafers","type_id":"L3nCd0aPr9pOAbKNaAcW","updatedAt":{"_seconds":1582534026,"_nanoseconds":142000000},"createdAt":{"_seconds":1582534026,"_nanoseconds":142000000}},{"title":"Clothing","updatedAt":{"_seconds":1590828081,"_nanoseconds":473000000},"type_ids":["szzkyPIEu3nOUb7BygdN"],"id":"2OHPg3ryamIHVUGtb0JY","createdAt":{"_seconds":1590828081,"_nanoseconds":473000000},"category_ids":["mskRjk1CHCvdWsURmmvz"]},{"category_ids":["mskRjk1CHCvdWsURmmvz"],"title":"Home decor","updatedAt":{"_seconds":1590827533,"_nanoseconds":754000000},"type_ids":["A7gx0MjZrkq3P86uD8RW"],"id":"2VZQChPdmYx0UrT5IuCm","createdAt":{"_seconds":1590827533,"_nanoseconds":754000000}},{"id":"2h3xLMzwhvYLdKixjHDK","createdAt":{"_seconds":1590828073,"_nanoseconds":253000000},"category_ids":["mskRjk1CHCvdWsURmmvz"],"title":"Accessories","updatedAt":{"_seconds":1590828073,"_nanoseconds":253000000},"type_ids":["szzkyPIEu3nOUb7BygdN"]},{"id":"31hq8Ve6ckhHKFizdFI1","type_id":"pjvJcy4IdmJ1ri4tvvXD","createdAt":{"_seconds":1587546253,"_nanoseconds":35000000},"category_ids":["g2llU0ofWnYUFdvSh7Tn"],"title":"Silk handkerchief","updatedAt":{"_seconds":1587546253,"_nanoseconds":35000000},"type_ids":["pjvJcy4IdmJ1ri4tvvXD"]},{"createdAt":{"_seconds":1590828052,"_nanoseconds":667000000},"category_ids":["mskRjk1CHCvdWsURmmvz"],"title":"Fitness","updatedAt":{"_seconds":1590828052,"_nanoseconds":667000000},"type_ids":["jrqlcgWPpLdXJbaygajD"],"id":"3UgEHDTumPFjAMNwFOiN"},{"category_ids":["g2llU0ofWnYUFdvSh7Tn"],"title":"Rings","updatedAt":{"_seconds":1587546397,"_nanoseconds":554000000},"type_ids":["Dzmxt8ehIp2ZLhBrXghY"],"id":"3z4aIVzTeUrwO6MNhkBU","type_id":"Dzmxt8ehIp2ZLhBrXghY","createdAt":{"_seconds":1587546397,"_nanoseconds":554000000}},{"type_ids":["7YTbSmuiLHH9Hcqr9iyh","d99jQZ70MLPPdk75i6ij","Eo2l5gIDLgjCKWLTR7Nw"],"id":"4LuxWFDyknxveYaI58Za","collection_ids":["wxm2cpK8UCMFaO49R69Q"],"image":{"src":"https://i.ibb.co/f1DWhDf/pngbarn.png"},"createdAt":{"_seconds":1590696913,"_nanoseconds":138000000},"category_ids":["OYruGwYUh0JRujWdc0iY","g2llU0ofWnYUFdvSh7Tn","xJeMcRLyhqL6NXz03orV"],"title":"Shorts","updatedAt":{"_seconds":1590696913,"_nanoseconds":138000000}},{"id":"57Zf7pcNS0P4rAxNRU0T","type_id":"Dzmxt8ehIp2ZLhBrXghY","createdAt":{"_seconds":1587546536,"_nanoseconds":134000000},"category_ids":["g2llU0ofWnYUFdvSh7Tn"],"title":"Hair accessories","updatedAt":{"_seconds":1587546536,"_nanoseconds":134000000},"type_ids":["Dzmxt8ehIp2ZLhBrXghY"]},{"createdAt":{"_seconds":1582537649,"_nanoseconds":22000000},"id":"5MFbdh7BMTDPTN5QEMY8","title":"Derby shoes","type_id":"ICORWzI1trn3O6wQBQwF","updatedAt":{"_seconds":1582537649,"_nanoseconds":22000000}},{"title":"Travel bags","updatedAt":{"_seconds":1587544939,"_nanoseconds":366000000},"type_ids":[" 8NUULeFjsycewAFgvx2X"],"id":"5PSu7lNBWHFuouUwC4Pr","type_id":" 8NUULeFjsycewAFgvx2X","category_ids":["g2llU0ofWnYUFdvSh7Tn"]},{"id":"5X3ZpMGjTAAKQ3gO2nSP","createdAt":{"_seconds":1590827778,"_nanoseconds":2000000},"category_ids":["mskRjk1CHCvdWsURmmvz"],"title":"Cycling","updatedAt":{"_seconds":1590827778,"_nanoseconds":2000000},"type_ids":["jrqlcgWPpLdXJbaygajD"]},{"updatedAt":{"_seconds":1587545685,"_nanoseconds":103000000},"type_ids":["d99jQZ70MLPPdk75i6ij"],"id":"65sg7Iy9yd8OZ9dZle6K","type_id":"d99jQZ70MLPPdk75i6ij","createdAt":{"_seconds":1587545685,"_nanoseconds":103000000},"category_ids":["g2llU0ofWnYUFdvSh7Tn"],"title":"Lingerie"},{"title":"Design","updatedAt":{"_seconds":1590827722,"_nanoseconds":642000000},"type_ids":["CF0uN3y5sZr9ZLnunaEy"],"id":"6GxRfc4CMb5nA8dyAma6","createdAt":{"_seconds":1590827722,"_nanoseconds":642000000},"category_ids":["mskRjk1CHCvdWsURmmvz"]},{"type_ids":["pjvJcy4IdmJ1ri4tvvXD"],"id":"6JRqqm6mKPIibktqSFdt","type_id":"pjvJcy4IdmJ1ri4tvvXD","createdAt":{"_seconds":1587546219,"_nanoseconds":880000000},"category_ids":["g2llU0ofWnYUFdvSh7Tn","xJeMcRLyhqL6NXz03orV"],"title":"Belts","updatedAt":{"_seconds":1587546219,"_nanoseconds":880000000}},{"id":"7rfZowHEr2z2UaAtwf65","type_id":"pjvJcy4IdmJ1ri4tvvXD","createdAt":{"_seconds":1587545744,"_nanoseconds":847000000},"category_ids":["g2llU0ofWnYUFdvSh7Tn","xJeMcRLyhqL6NXz03orV"],"title":"Sungslasses","updatedAt":{"_seconds":1587545744,"_nanoseconds":847000000}},{"updatedAt":{"_seconds":1590780064,"_nanoseconds":488000000},"type_ids":["pjvJcy4IdmJ1ri4tvvXD"],"id":"877LVvtyqm8ly4vxI02K","createdAt":{"_seconds":1590780064,"_nanoseconds":488000000},"category_ids":["OYruGwYUh0JRujWdc0iY","g2llU0ofWnYUFdvSh7Tn","xJeMcRLyhqL6NXz03orV"],"title":"Sunglasses"},{"createdAt":{"_seconds":1587546590,"_nanoseconds":424000000},"category_ids":["g2llU0ofWnYUFdvSh7Tn"],"title":"Bag charms","updatedAt":{"_seconds":1587546590,"_nanoseconds":424000000},"type_ids":["Dzmxt8ehIp2ZLhBrXghY"],"id":"8p7RJbNx8aLii3YfVRwO","type_id":"Dzmxt8ehIp2ZLhBrXghY"},{"id":"8zzg5C4u1Qgjr2WCVbAe","createdAt":{"_seconds":1590827827,"_nanoseconds":137000000},"category_ids":["mskRjk1CHCvdWsURmmvz"],"title":"Tennis","updatedAt":{"_seconds":1590827827,"_nanoseconds":137000000},"type_ids":["jrqlcgWPpLdXJbaygajD"]},{"updatedAt":{"_seconds":1590827699,"_nanoseconds":127000000},"type_ids":["CF0uN3y5sZr9ZLnunaEy"],"id":"ABopRfVBM1193EbbVZLT","createdAt":{"_seconds":1590827699,"_nanoseconds":127000000},"category_ids":["mskRjk1CHCvdWsURmmvz"],"title":"Photography"},{"id":"AEXg5oFP3zfPysbPIbFW","title":"Baskets","type_id":"ICORWzI1trn3O6wQBQwF","updatedAt":{"_seconds":1582537342,"_nanoseconds":862000000},"createdAt":{"_seconds":1582537342,"_nanoseconds":862000000}},{"id":"B9M1HQrVoZjzaq5uazpn","type_id":"d99jQZ70MLPPdk75i6ij","createdAt":{"_seconds":1582533583,"_nanoseconds":942000000},"category_ids":["g2llU0ofWnYUFdvSh7Tn"],"typey_id":"d99jQZ70MLPPdk75i6ij","title":"Jumpsuits","updatedAt":{"_seconds":1582533583,"_nanoseconds":942000000},"type_ids":["d99jQZ70MLPPdk75i6ij"]},{"title":"Ballet Flats","updatedAt":{"_seconds":1582538381,"_nanoseconds":489000000},"id":"BHsJYO1g5YT4QISL2h2N","type_id":"L3nCd0aPr9pOAbKNaAcW","createdAt":{"_seconds":1582538381,"_nanoseconds":489000000},"category_ids":["g2llU0ofWnYUFdvSh7Tn"]},{"id":"BZbih54FOlWRBJPsvqbU","createdAt":{"_seconds":1590827766,"_nanoseconds":484000000},"category_ids":["mskRjk1CHCvdWsURmmvz"],"title":"Boards","updatedAt":{"_seconds":1590827766,"_nanoseconds":484000000},"type_ids":["jrqlcgWPpLdXJbaygajD"]},{"createdAt":{"_seconds":1587545768,"_nanoseconds":5000000},"category_ids":["g2llU0ofWnYUFdvSh7Tn","xJeMcRLyhqL6NXz03orV"],"title":"Wallets","updatedAt":{"_seconds":1587545768,"_nanoseconds":5000000},"type_ids":["pjvJcy4IdmJ1ri4tvvXD"],"id":"CArEYiN6TolC9kui7rFu","type_id":"pjvJcy4IdmJ1ri4tvvXD"},{"category_ids":["g2llU0ofWnYUFdvSh7Tn","xJeMcRLyhqL6NXz03orV"],"title":"Coats","updatedAt":{"_seconds":1587545591,"_nanoseconds":239000000},"type_ids":["d99jQZ70MLPPdk75i6ij"],"id":"DXKeibr5fm8mIy65AoEB","type_id":"d99jQZ70MLPPdk75i6ij","createdAt":{"_seconds":1587545591,"_nanoseconds":239000000}},{"updatedAt":{"_seconds":1587546493,"_nanoseconds":40000000},"type_ids":["Dzmxt8ehIp2ZLhBrXghY"],"id":"EMu9cjjK1sliBLDAIA9A","type_id":"Dzmxt8ehIp2ZLhBrXghY","createdAt":{"_seconds":1587546493,"_nanoseconds":40000000},"category_ids":["g2llU0ofWnYUFdvSh7Tn"],"title":"Pendants"},{"id":"FHHJpEqidsIJCcEx1naa","createdAt":{"_seconds":1590696951,"_nanoseconds":271000000},"category_ids":["OYruGwYUh0JRujWdc0iY"],"title":"Jackets & coats","updatedAt":{"_seconds":1590696951,"_nanoseconds":271000000},"type_ids":["7YTbSmuiLHH9Hcqr9iyh","Eo2l5gIDLgjCKWLTR7Nw"]},{"title":"Accessories","updatedAt":{"_seconds":1590828063,"_nanoseconds":154000000},"type_ids":["FihU6GTXWUu9SelqLvxi"],"id":"FVFCuJyyUX6KikIchxKR","createdAt":{"_seconds":1590828063,"_nanoseconds":154000000},"category_ids":["mskRjk1CHCvdWsURmmvz"]},{"updatedAt":{"_seconds":1582537756,"_nanoseconds":192000000},"createdAt":{"_seconds":1582537756,"_nanoseconds":192000000},"id":"G6D3ebbY1BT4roZuUGqo","title":"Satchel","type_id":"Ufg6Eag6C0DopkJeRSzc"},{"id":"GxNgiKgHQhsCAlUEF6tk","type_id":"Eo2l5gIDLgjCKWLTR7Nw","category_ids":["g2llU0ofWnYUFdvSh7Tn","OYruGwYUh0JRujWdc0iY"],"title":"Dresses","updatedAt":{"_seconds":1590697065,"_nanoseconds":898000000},"type_ids":["d99jQZ70MLPPdk75i6ij","Eo2l5gIDLgjCKWLTR7Nw"]},{"createdAt":{"_seconds":1590827446,"_nanoseconds":812000000},"category_ids":["mskRjk1CHCvdWsURmmvz"],"title":"Dinnerware","updatedAt":{"_seconds":1590827446,"_nanoseconds":812000000},"type_ids":["A7gx0MjZrkq3P86uD8RW"],"id":"LxLeIHy5ssrOmLzZMWVq"},{"title":"Derby shoes","type_id":"L3nCd0aPr9pOAbKNaAcW","updatedAt":{"_seconds":1582538424,"_nanoseconds":70000000},"createdAt":{"_seconds":1582538424,"_nanoseconds":70000000},"id":"NfjD4Kp79ndKpGokmCT3"},{"id":"P0XlMYb6mQABEgoyl9BR","createdAt":{"_seconds":1590827150,"_nanoseconds":372000000},"category_ids":["xJeMcRLyhqL6NXz03orV"],"title":"Ties","updatedAt":{"_seconds":1590827150,"_nanoseconds":372000000},"type_ids":["pjvJcy4IdmJ1ri4tvvXD"]},{"id":"PAFQhiTDa3HoYEuQSdHi","createdAt":{"_seconds":1590781018,"_nanoseconds":514000000},"category_ids":["g2llU0ofWnYUFdvSh7Tn"],"title":"Mules & clogs","updatedAt":{"_seconds":1590781018,"_nanoseconds":514000000},"type_ids":["L3nCd0aPr9pOAbKNaAcW"]},{"createdAt":{"_seconds":1587545026,"_nanoseconds":478000000},"category_ids":["g2llU0ofWnYUFdvSh7Tn","OYruGwYUh0JRujWdc0iY","xJeMcRLyhqL6NXz03orV"],"title":"Flats","updatedAt":{"_seconds":1587545026,"_nanoseconds":478000000},"type_ids":["L3nCd0aPr9pOAbKNaAcW"],"id":"PahLOvxXTlNiZykqI3Ak","type_id":"L3nCd0aPr9pOAbKNaAcW"},{"type_ids":[" 8NUULeFjsycewAFgvx2X"],"id":"PmaPRlxu914DwTSH7Tic","type_id":" 8NUULeFjsycewAFgvx2X","category_ids":["g2llU0ofWnYUFdvSh7Tn"],"title":"Backpacks","updatedAt":{"_seconds":1587544930,"_nanoseconds":809000000}},{"category_ids":["mskRjk1CHCvdWsURmmvz"],"title":"Art","updatedAt":{"_seconds":1590827712,"_nanoseconds":96000000},"type_ids":["CF0uN3y5sZr9ZLnunaEy"],"id":"Qj6iIskDAT12AgSJTSda","createdAt":{"_seconds":1590827712,"_nanoseconds":96000000}},{"title":"Lace ups","updatedAt":{"_seconds":1587545201,"_nanoseconds":483000000},"type_ids":["L3nCd0aPr9pOAbKNaAcW"],"id":"RXvQUXhXuD6sTmjyT9W1","type_id":"L3nCd0aPr9pOAbKNaAcW","createdAt":{"_seconds":1587545201,"_nanoseconds":483000000},"category_ids":["g2llU0ofWnYUFdvSh7Tn","xJeMcRLyhqL6NXz03orV"]},{"title":"Knitwear & sweatshirts","updatedAt":{"_seconds":1590823793,"_nanoseconds":591000000},"type_ids":["d99jQZ70MLPPdk75i6ij"],"id":"RpJ2uGnc3AYnBt87hRzX","createdAt":{"_seconds":1590823793,"_nanoseconds":591000000},"category_ids":["xJeMcRLyhqL6NXz03orV"]},{"id":"SAgSVlPs6IMLxOxbE1cd","createdAt":{"_seconds":1590823827,"_nanoseconds":461000000},"category_ids":["xJeMcRLyhqL6NXz03orV"],"title":"Suits","updatedAt":{"_seconds":1590823827,"_nanoseconds":461000000},"type_ids":["d99jQZ70MLPPdk75i6ij"]},{"title":"Playground","updatedAt":{"_seconds":1590828089,"_nanoseconds":426000000},"type_ids":["szzkyPIEu3nOUb7BygdN"],"id":"SolZxcpxhiMlK33cDTlu","createdAt":{"_seconds":1590828089,"_nanoseconds":426000000},"category_ids":["mskRjk1CHCvdWsURmmvz"]},{"id":"TUpZfwnjtuhzFMe1xknw","createdAt":{"_seconds":1590696937,"_nanoseconds":292000000},"category_ids":["OYruGwYUh0JRujWdc0iY","g2llU0ofWnYUFdvSh7Tn","xJeMcRLyhqL6NXz03orV"],"title":"Knitwear","updatedAt":{"_seconds":1590696937,"_nanoseconds":292000000},"type_ids":["7YTbSmuiLHH9Hcqr9iyh","Eo2l5gIDLgjCKWLTR7Nw","d99jQZ70MLPPdk75i6ij"]},{"title":"Fashion","updatedAt":{"_seconds":1590827752,"_nanoseconds":574000000},"type_ids":["CF0uN3y5sZr9ZLnunaEy"],"id":"UuXWUjRYMhrPjBXLOShS","createdAt":{"_seconds":1590827752,"_nanoseconds":574000000},"category_ids":["mskRjk1CHCvdWsURmmvz"]},{"id":"V9X1BKzFvI3T5j099ION","createdAt":{"_seconds":1590780033,"_nanoseconds":840000000},"category_ids":["OYruGwYUh0JRujWdc0iY"],"title":"First shoes","updatedAt":{"_seconds":1590780033,"_nanoseconds":840000000},"type_ids":["L3nCd0aPr9pOAbKNaAcW"]},{"id":"VRUeYNKv8koubg9BmHXB","type_id":"pjvJcy4IdmJ1ri4tvvXD","createdAt":{"_seconds":1587546349,"_nanoseconds":817000000},"category_ids":["g2llU0ofWnYUFdvSh7Tn","xJeMcRLyhqL6NXz03orV"],"title":"Gloves","updatedAt":{"_seconds":1587546349,"_nanoseconds":817000000},"type_ids":["pjvJcy4IdmJ1ri4tvvXD"]},{"category_ids":["g2llU0ofWnYUFdvSh7Tn"],"title":"Trench coats","updatedAt":{"_seconds":1587545665,"_nanoseconds":883000000},"type_ids":["d99jQZ70MLPPdk75i6ij"],"id":"VhINPrBqjM7Q279Qgs6U","type_id":"d99jQZ70MLPPdk75i6ij","createdAt":{"_seconds":1587545665,"_nanoseconds":883000000}},{"title":"Tops","updatedAt":{"_seconds":1590696925,"_nanoseconds":344000000},"type_ids":["7YTbSmuiLHH9Hcqr9iyh","Eo2l5gIDLgjCKWLTR7Nw","d99jQZ70MLPPdk75i6ij"],"id":"VlHpU10gm2auF3BK4mGm","createdAt":{"_seconds":1590696925,"_nanoseconds":344000000},"category_ids":["OYruGwYUh0JRujWdc0iY","g2llU0ofWnYUFdvSh7Tn"]},{"title":"Clutch bags","updatedAt":{"_seconds":1587544916,"_nanoseconds":868000000},"type_ids":[" 8NUULeFjsycewAFgvx2X"],"id":"WTrZf7tMPoGm1LnrrOg7","type_id":" 8NUULeFjsycewAFgvx2X","category_ids":["g2llU0ofWnYUFdvSh7Tn"]},{"title":"Ankle boots","updatedAt":{"_seconds":1590781083,"_nanoseconds":306000000},"type_ids":["L3nCd0aPr9pOAbKNaAcW"],"id":"YIsq18X0lnfpaDmqhWcP","createdAt":{"_seconds":1590781083,"_nanoseconds":306000000},"category_ids":["g2llU0ofWnYUFdvSh7Tn"]},{"category_ids":["g2llU0ofWnYUFdvSh7Tn"],"title":"Earrings","updatedAt":{"_seconds":1587546523,"_nanoseconds":144000000},"id":"YY2jJfOCyLDUPQTCBe2O","type_id":"Dzmxt8ehIp2ZLhBrXghY","createdAt":{"_seconds":1587546523,"_nanoseconds":144000000}},{"title":"Phone charms","updatedAt":{"_seconds":1587546605,"_nanoseconds":998000000},"type_ids":["Dzmxt8ehIp2ZLhBrXghY"],"id":"Yu38SGhCoqUGtKXDowTh","type_id":"Dzmxt8ehIp2ZLhBrXghY","createdAt":{"_seconds":1587546605,"_nanoseconds":998000000},"category_ids":["g2llU0ofWnYUFdvSh7Tn"]},{"createdAt":{"_seconds":1582533505,"_nanoseconds":319000000},"category_ids":["g2llU0ofWnYUFdvSh7Tn","OYruGwYUh0JRujWdc0iY"],"typey_id":"d99jQZ70MLPPdk75i6ij","title":"Skirts","updatedAt":{"_seconds":1582533505,"_nanoseconds":319000000},"type_ids":["d99jQZ70MLPPdk75i6ij","Eo2l5gIDLgjCKWLTR7Nw"],"id":"ZFnwh5yqJjuQNjWHs72e","type_id":"d99jQZ70MLPPdk75i6ij"},{"category_ids":["g2llU0ofWnYUFdvSh7Tn"],"title":"Handbags","updatedAt":{"_seconds":1587544903,"_nanoseconds":697000000},"type_ids":[" 8NUULeFjsycewAFgvx2X"],"id":"ZckAr4dKkCgtfr209P7L","type_id":" 8NUULeFjsycewAFgvx2X"},{"id":"ZrchedgNZ0gmcv3KJkrT","createdAt":{"_seconds":1590780144,"_nanoseconds":949000000},"category_ids":["OYruGwYUh0JRujWdc0iY"],"title":"Hats & gloves","updatedAt":{"_seconds":1590780144,"_nanoseconds":949000000},"type_ids":["pjvJcy4IdmJ1ri4tvvXD"]},{"title":"Bags","updatedAt":{"_seconds":1590827080,"_nanoseconds":962000000},"type_ids":[" 8NUULeFjsycewAFgvx2X"],"id":"Zu944VWzlRxvMj8qlQ7p","createdAt":{"_seconds":1590827080,"_nanoseconds":962000000},"category_ids":["xJeMcRLyhqL6NXz03orV"]},{"title":"Scarves & pocket squares","updatedAt":{"_seconds":1590827135,"_nanoseconds":359000000},"type_ids":["pjvJcy4IdmJ1ri4tvvXD"],"id":"aicF4DEhmJEk3mBZJVpP","createdAt":{"_seconds":1590827135,"_nanoseconds":359000000},"category_ids":["xJeMcRLyhqL6NXz03orV"]},{"id":"atTQ6a3TKYRbZ4PDhUSB","type_id":"L3nCd0aPr9pOAbKNaAcW","createdAt":{"_seconds":1582534014,"_nanoseconds":326000000},"category_ids":["g2llU0ofWnYUFdvSh7Tn","OYruGwYUh0JRujWdc0iY","xJeMcRLyhqL6NXz03orV"],"typey_id":"L3nCd0aPr9pOAbKNaAcW","title":"Trainers","updatedAt":{"_seconds":1582534014,"_nanoseconds":326000000},"type_ids":["L3nCd0aPr9pOAbKNaAcW"]},{"category_ids":["xJeMcRLyhqL6NXz03orV"],"title":"T-shirts","updatedAt":{"_seconds":1590823757,"_nanoseconds":787000000},"type_ids":["d99jQZ70MLPPdk75i6ij"],"id":"bcx7LDCVXMErc18vmnrx","createdAt":{"_seconds":1590823757,"_nanoseconds":787000000}},{"category_ids":["g2llU0ofWnYUFdvSh7Tn"],"title":"Bracelets","updatedAt":{"_seconds":1587546417,"_nanoseconds":268000000},"type_ids":["Dzmxt8ehIp2ZLhBrXghY"],"id":"biNcJt3L5QGavO9hjBfD","type_id":"Dzmxt8ehIp2ZLhBrXghY","createdAt":{"_seconds":1587546417,"_nanoseconds":268000000}},{"id":"btvY7hIQIT2kgk2sxPpP","type_id":"Dzmxt8ehIp2ZLhBrXghY","createdAt":{"_seconds":1587546509,"_nanoseconds":949000000},"category_ids":["g2llU0ofWnYUFdvSh7Tn"],"title":"Long necklaces","updatedAt":{"_seconds":1587546509,"_nanoseconds":949000000},"type_ids":["Dzmxt8ehIp2ZLhBrXghY"]},{"title":"Shirts","updatedAt":{"_seconds":1587543110,"_nanoseconds":21000000},"type_ids":["d99jQZ70MLPPdk75i6ij"],"id":"buFTdM986I9gBnAa04p1","type_id":"d99jQZ70MLPPdk75i6ij","createdAt":{"_seconds":1587543110,"_nanoseconds":21000000},"category_ids":["xJeMcRLyhqL6NXz03orV"]},{"title":"Cufflinks","updatedAt":{"_seconds":1590827190,"_nanoseconds":649000000},"type_ids":["pjvJcy4IdmJ1ri4tvvXD"],"id":"c9VTdND92P1SaQ2GIAW8","createdAt":{"_seconds":1590827190,"_nanoseconds":649000000},"category_ids":["xJeMcRLyhqL6NXz03orV"]},{"id":"d4UiG9BLPGvmvhHyif3j","type_id":"d99jQZ70MLPPdk75i6ij","createdAt":{"_seconds":1587545698,"_nanoseconds":921000000},"category_ids":["g2llU0ofWnYUFdvSh7Tn"],"title":"Swimwaear","updatedAt":{"_seconds":1587545698,"_nanoseconds":921000000}},{"id":"dHgX7Yu4klKuHuJ1FG3c","createdAt":{"_seconds":1590780090,"_nanoseconds":983000000},"category_ids":["OYruGwYUh0JRujWdc0iY"],"title":"Belts, suspenders","updatedAt":{"_seconds":1590780090,"_nanoseconds":983000000},"type_ids":["pjvJcy4IdmJ1ri4tvvXD"]},{"id":"dKju3nuKRwjhGnD87dnZ","type_id":"L3nCd0aPr9pOAbKNaAcW","createdAt":{"_seconds":1582538451,"_nanoseconds":206000000},"category_ids":["g2llU0ofWnYUFdvSh7Tn"],"title":"Ankle Boots","updatedAt":{"_seconds":1582538451,"_nanoseconds":206000000}},{"type_id":"L3nCd0aPr9pOAbKNaAcW","createdAt":{"_seconds":1582538413,"_nanoseconds":114000000},"category_ids":["g2llU0ofWnYUFdvSh7Tn"],"title":"Mules & Clogs","updatedAt":{"_seconds":1582538413,"_nanoseconds":114000000},"id":"dhg1dEGFGOfkykt2rgyE"},{"createdAt":{"_seconds":1590823662,"_nanoseconds":795000000},"category_ids":["g2llU0ofWnYUFdvSh7Tn"],"title":"Earnings","updatedAt":{"_seconds":1590823662,"_nanoseconds":795000000},"type_ids":["Dzmxt8ehIp2ZLhBrXghY"],"id":"e9JRf4c7t7NkdvRWBhvv"},{"id":"eWHYiN2ajMBE2FfcHkN8","title":"Week-end bags","type_id":"Ufg6Eag6C0DopkJeRSzc","updatedAt":{"_seconds":1582537941,"_nanoseconds":912000000},"createdAt":{"_seconds":1582537941,"_nanoseconds":912000000}},{"category_ids":["OYruGwYUh0JRujWdc0iY","xJeMcRLyhqL6NXz03orV"],"title":"Jewellery","updatedAt":{"_seconds":1590780787,"_nanoseconds":554000000},"type_ids":["pjvJcy4IdmJ1ri4tvvXD"],"id":"enHORJH1SXnUAXFyDyDP","createdAt":{"_seconds":1590780787,"_nanoseconds":554000000}},{"category_ids":["g2llU0ofWnYUFdvSh7Tn","xJeMcRLyhqL6NXz03orV"],"title":"Jackets","updatedAt":{"_seconds":1587545576,"_nanoseconds":90000000},"type_ids":["d99jQZ70MLPPdk75i6ij"],"id":"hFdLtCZVLhf6iowOmYro","type_id":"d99jQZ70MLPPdk75i6ij","createdAt":{"_seconds":1587545576,"_nanoseconds":90000000}},{"title":"Jeans","updatedAt":{"_seconds":1587545490,"_nanoseconds":536000000},"type_ids":["d99jQZ70MLPPdk75i6ij"],"id":"hcNKTRD1rFWRlUbrKjRS","type_id":"d99jQZ70MLPPdk75i6ij","createdAt":{"_seconds":1587545490,"_nanoseconds":536000000},"category_ids":["g2llU0ofWnYUFdvSh7Tn","xJeMcRLyhqL6NXz03orV"]},{"createdAt":{"_seconds":1587546295,"_nanoseconds":225000000},"category_ids":["g2llU0ofWnYUFdvSh7Tn"],"title":"Purses, wallets & cases","updatedAt":{"_seconds":1587546295,"_nanoseconds":225000000},"type_ids":["pjvJcy4IdmJ1ri4tvvXD"],"id":"ikhqOgXO3Sxg34vWSv1J","type_id":"pjvJcy4IdmJ1ri4tvvXD"},{"createdAt":{"_seconds":1590779967,"_nanoseconds":36000000},"category_ids":["OYruGwYUh0JRujWdc0iY"],"title":"Lace up boots","updatedAt":{"_seconds":1590779967,"_nanoseconds":36000000},"type_ids":["L3nCd0aPr9pOAbKNaAcW"],"id":"j2yyO1znkI9RoGZ6HaRE"},{"type_ids":["Dzmxt8ehIp2ZLhBrXghY"],"id":"jsAISMoS1zkGCRZqWQ51","createdAt":{"_seconds":1590823641,"_nanoseconds":858000000},"category_ids":["g2llU0ofWnYUFdvSh7Tn"],"title":"Jewellery sets sets","updatedAt":{"_seconds":1590823641,"_nanoseconds":858000000}},{"id":"kV04jaK42fn8DrbrpMkM","createdAt":{"_seconds":1590827813,"_nanoseconds":592000000},"category_ids":["mskRjk1CHCvdWsURmmvz"],"title":"Sport balls","updatedAt":{"_seconds":1590827813,"_nanoseconds":592000000},"type_ids":["jrqlcgWPpLdXJbaygajD"]},{"type_ids":["L3nCd0aPr9pOAbKNaAcW"],"id":"kevWB7prKtDlgE9Gy03K","createdAt":{"_seconds":1590779845,"_nanoseconds":272000000},"category_ids":["OYruGwYUh0JRujWdc0iY","g2llU0ofWnYUFdvSh7Tn"],"title":"Ballet flats","updatedAt":{"_seconds":1590779845,"_nanoseconds":272000000}},{"createdAt":{"_seconds":1590781390,"_nanoseconds":271000000},"category_ids":["xJeMcRLyhqL6NXz03orV","g2llU0ofWnYUFdvSh7Tn"],"title":"Swimwear","updatedAt":{"_seconds":1590781390,"_nanoseconds":271000000},"type_ids":["d99jQZ70MLPPdk75i6ij"],"id":"l57uHELmkI2lO9qZQIoc"},{"type_ids":["jrqlcgWPpLdXJbaygajD"],"id":"m3c6rHzOjuJSJqaG9wh9","createdAt":{"_seconds":1590827790,"_nanoseconds":89000000},"category_ids":["mskRjk1CHCvdWsURmmvz"],"title":"Golf","updatedAt":{"_seconds":1590827790,"_nanoseconds":89000000}},{"id":"ocL5xs4ORWnvqRgs0cx6","type_id":"pjvJcy4IdmJ1ri4tvvXD","createdAt":{"_seconds":1587546279,"_nanoseconds":518000000},"category_ids":["g2llU0ofWnYUFdvSh7Tn","OYruGwYUh0JRujWdc0iY"],"title":"Scarves","updatedAt":{"_seconds":1587546279,"_nanoseconds":518000000},"type_ids":["pjvJcy4IdmJ1ri4tvvXD"]},{"id":"q1I5Uh4XNRq8xC7E6y5t","type_id":"pjvJcy4IdmJ1ri4tvvXD","createdAt":{"_seconds":1587546267,"_nanoseconds":143000000},"category_ids":["g2llU0ofWnYUFdvSh7Tn","xJeMcRLyhqL6NXz03orV"],"title":"Hats","updatedAt":{"_seconds":1587546267,"_nanoseconds":143000000},"type_ids":["pjvJcy4IdmJ1ri4tvvXD"]},{"id":"rJV1ndzss6yJ4BviBfgd","createdAt":{"_seconds":1590823746,"_nanoseconds":17000000},"category_ids":["xJeMcRLyhqL6NXz03orV"],"title":"Polo shirts","updatedAt":{"_seconds":1590823746,"_nanoseconds":17000000},"type_ids":["d99jQZ70MLPPdk75i6ij"]},{"title":"Outfits","updatedAt":{"_seconds":1590690354,"_nanoseconds":145000000},"type_ids":["7YTbSmuiLHH9Hcqr9iyh","Eo2l5gIDLgjCKWLTR7Nw"],"id":"rxpx60EO3hXLSzBW5wX9","type_id":"7YTbSmuiLHH9Hcqr9iyh","createdAt":{"_seconds":1590690354,"_nanoseconds":145000000},"category_ids":["OYruGwYUh0JRujWdc0iY"]},{"id":"s8Kp1wRq2eYiJclrsiOb","createdAt":{"_seconds":1590779788,"_nanoseconds":68000000},"category_ids":["OYruGwYUh0JRujWdc0iY"],"title":"Slippers","updatedAt":{"_seconds":1590779788,"_nanoseconds":68000000},"type_ids":["L3nCd0aPr9pOAbKNaAcW"]},{"title":"Hats & pull on hats","updatedAt":{"_seconds":1590827208,"_nanoseconds":671000000},"type_ids":["pjvJcy4IdmJ1ri4tvvXD"],"id":"scGg59mM2GCrlO7OfKTc","createdAt":{"_seconds":1590827208,"_nanoseconds":671000000},"category_ids":["xJeMcRLyhqL6NXz03orV"]},{"type_ids":[" 8NUULeFjsycewAFgvx2X"],"id":"tCEyh2JMmVIrVlkUoRgM","createdAt":{"_seconds":1590827096,"_nanoseconds":196000000},"category_ids":["xJeMcRLyhqL6NXz03orV"],"title":"Small bags, wallets & cases","updatedAt":{"_seconds":1590827096,"_nanoseconds":196000000}},{"id":"uOtHVOeBUg8400d7ioSn","type_id":"d99jQZ70MLPPdk75i6ij","collection_ids":["wxm2cpK8UCMFaO49R69Q"],"image":{"src":"https://firebasestorage.googleapis.com/v0/b/clother-shop.appspot.com/o/subtypes%2Ftrousers.png?alt=media&token=2ffceb68-346e-4809-a803-7e70bed74adc"},"createdAt":{"_seconds":1582533548,"_nanoseconds":585000000},"category_ids":["g2llU0ofWnYUFdvSh7Tn","xJeMcRLyhqL6NXz03orV","OYruGwYUh0JRujWdc0iY"],"typey_id":"d99jQZ70MLPPdk75i6ij","title":"Trousers","updatedAt":{"_seconds":1582533548,"_nanoseconds":585000000},"type_ids":["d99jQZ70MLPPdk75i6ij","7YTbSmuiLHH9Hcqr9iyh","Eo2l5gIDLgjCKWLTR7Nw"]},{"category_ids":["g2llU0ofWnYUFdvSh7Tn"],"title":"Leather jackets","updatedAt":{"_seconds":1587545651,"_nanoseconds":523000000},"type_ids":["d99jQZ70MLPPdk75i6ij"],"id":"vAEcfaQV0Ht6Ctf9oG43","type_id":"d99jQZ70MLPPdk75i6ij","createdAt":{"_seconds":1587545651,"_nanoseconds":523000000}},{"title":"Boots","updatedAt":{"_seconds":1582537667,"_nanoseconds":830000000},"type_ids":["L3nCd0aPr9pOAbKNaAcW"],"id":"w6ZvvVaoVz1el7VuvgWQ","type_id":"L3nCd0aPr9pOAbKNaAcW","category_id":"xJeMcRLyhqL6NXz03orV","createdAt":{"_seconds":1582537667,"_nanoseconds":830000000},"category_ids":["xJeMcRLyhqL6NXz03orV","OYruGwYUh0JRujWdc0iY","g2llU0ofWnYUFdvSh7Tn"]},{"id":"wRvFQfLKiqaulgVhMq0h","createdAt":{"_seconds":1590827514,"_nanoseconds":658000000},"category_ids":["mskRjk1CHCvdWsURmmvz"],"title":"Textiles","updatedAt":{"_seconds":1590827514,"_nanoseconds":658000000},"type_ids":["A7gx0MjZrkq3P86uD8RW"]},{"title":"Swimming","updatedAt":{"_seconds":1590827801,"_nanoseconds":328000000},"type_ids":["jrqlcgWPpLdXJbaygajD"],"id":"wdNnWizIt7vvZsLr9UVP","createdAt":{"_seconds":1590827801,"_nanoseconds":328000000},"category_ids":["mskRjk1CHCvdWsURmmvz"]},{"title":"Bags & pencil cases","updatedAt":{"_seconds":1590780162,"_nanoseconds":677000000},"type_ids":["pjvJcy4IdmJ1ri4tvvXD"],"id":"wz53jJkY3jycpddf9fEG","createdAt":{"_seconds":1590780162,"_nanoseconds":677000000},"category_ids":["OYruGwYUh0JRujWdc0iY"]},{"collection_ids":[],"category_id":"xJeMcRLyhqL6NXz03orV","image":{"src":"https://cdn.shopify.com/s/files/1/2698/1188/products/933c20edd27db2e3c7ea62ed1dc6d0cf_1800x1800.png?v=1549975222"},"createdAt":{"_seconds":1582537695,"_nanoseconds":89000000},"category_ids":["xJeMcRLyhqL6NXz03orV","g2llU0ofWnYUFdvSh7Tn"],"title":"Espadrilles","updatedAt":{"_seconds":1582537695,"_nanoseconds":89000000},"type_ids":["L3nCd0aPr9pOAbKNaAcW"],"id":"yWKOYybJR7rE0TPuqvtc","type_id":"L3nCd0aPr9pOAbKNaAcW"},{"updatedAt":{"_seconds":1587546437,"_nanoseconds":212000000},"type_ids":["Dzmxt8ehIp2ZLhBrXghY"],"id":"ymbPV7xTVpCPJVybzbGG","type_id":"Dzmxt8ehIp2ZLhBrXghY","createdAt":{"_seconds":1587546437,"_nanoseconds":212000000},"category_ids":["g2llU0ofWnYUFdvSh7Tn"],"title":"Pins & brooches"},{"type_id":"L3nCd0aPr9pOAbKNaAcW","collection_ids":["wxm2cpK8UCMFaO49R69Q"],"category_id":"xJeMcRLyhqL6NXz03orV","image":{"src":"https://firebasestorage.googleapis.com/v0/b/clother-shop.appspot.com/o/subtypes%2Fsandals.png?alt=media&token=26c098fb-66af-4844-bbff-21f8de0ff438"},"createdAt":{"_seconds":1582537681,"_nanoseconds":874000000},"category_ids":["xJeMcRLyhqL6NXz03orV","g2llU0ofWnYUFdvSh7Tn","OYruGwYUh0JRujWdc0iY"],"title":"Sandals","updatedAt":{"_seconds":1582537681,"_nanoseconds":874000000},"type_ids":["L3nCd0aPr9pOAbKNaAcW"],"id":"zDn7ISgrx1jM109XMcpc"}]